[
    {
        "_id": "1",
        "title": "Amul Gold Full Cream Milk",
        "quantity": "500 ml",
        "mrp": "35",
        "price": "32",
        "category": "Dairy, Bread & Eggs",
        "image": "Images/milk.png"
    },
    {
        "_id": "2",
        "title": "Amul Masti Pouch Curd",
        "quantity": "390 g",
        "mrp": "35",
        "price": "32",
        "category": "Dairy, Bread & Eggs",
        "image": "Images/whey.png"
    },
    {
        "_id": "3",
        "title": "Amul Salted Butter",
        "quantity": "100 g",
        "mrp": "58",
        "price": "54",
        "category": "Dairy, Bread & Eggs",
        "image": "Images/butter.png"
    },
    {
        "_id": "4",
        "title": "Good Morning Malai Milk Bread",
        "quantity": "400 g",
        "mrp": "40",
        "price": "40",
        "category": "Dairy, Bread & Eggs",
        "image": "Images/good-morning.png"
    },
    {
        "_id": "5",
        "title": "Amul Taza Toned Milk",
        "quantity": "500 ml",
        "mrp": "29",
        "price": "29",
        "category": "Dairy, Bread & Eggs",
        "image": "Images/amul-toned.png"
    },
    {
        "_id": "6",
        "title": "English Oven Premium White Bread 350 g",
        "quantity": "350 g",
        "mrp": "30",
        "price": "27",
        "category": "Dairy, Bread & Eggs",
        "image": "Images/81136a7e-0681-4376-a109-92550ae66877.png"
    },
    {
        "_id": "7",
        "title": "Amul Cow Milk",
        "quantity": "500 ml",
        "mrp": "30",
        "price": "32",
        "category": "Dairy, Bread & Eggs",
        "image": "Images/ae29e828-f5d9-4f8b-89b6-8c6d6919df7b.png"
    },
    {
        "_id": "8",
        "title": "BranO Shaanegomti Premium White Bread",
        "quantity": "360 g (13 pieces)",
        "mrp": "40",
        "price": "40",
        "category": "Dairy, Bread & Eggs",
        "image": "Images/a858c12c-b0d7-408f-811c-52ed8c9b7223.png"
    },
    {
        "_id": "9",
        "title": "Amul Masti Cup Curd",
        "quantity": "200 g",
        "mrp": "120",
        "price": "120",
        "category": "Dairy, Bread & Eggs",
        "image": "Images/e47341cd-d920-4c0a-a9f2-20d663976cd0.png"
    },
    {
        "_id": "10",
        "title": "Amul Blend Diced Cheese",
        "quantity": "500 ml",
        "mrp": "35",
        "price": "32",
        "category": "Dairy, Bread & Eggs",
        "image": "Images/dfa345bf-052e-4657-ae4f-859bfe45fecf.png"
    },
    {
        "_id": "11",
        "title": "Amul Salted Butter",
        "quantity": "200 g",
        "mrp": "119",
        "price": "118",
        "category": "Dairy, Bread & Eggs",
        "image": "Images/03af3633-5fa5-438f-bece-145ed114d279.png"
    },
    {
        "_id": "12",
        "title": "Amul Cheese Slices",
        "quantity": "200 g",
        "mrp": "140",
        "price": "140",
        "category": "Dairy, Bread & Eggs",
        "image": "Images/a501e65f-194b-4db2-abc9-6b7bb515349c.png"
    },
    {
        "_id": "13",
        "title": "Amul Masti Pouch Curd",
        "quantity": "1 kg",
        "mrp": "77",
        "price": "77",
        "category": "Dairy, Bread & Eggs",
        "image": "Images/e7023096-622d-4e2e-9c2c-a7689262c36f.png"
    },
    {
        "_id": "14",
        "title": "BranO Bombay Pav",
        "quantity": "250 g",
        "mrp": "40",
        "price": "40",
        "category": "Dairy, Bread & Eggs",
        "image": "Images/d619dafc-96bc-4bd2-8e5b-f7f80c963431.png"
    },
    {
        "_id": "15",
        "title": "BranO Plus Brown Bread",
        "quantity": "270 g",
        "mrp": "35",
        "price": "35",
        "category": "Dairy, Bread & Eggs",
        "image": "Images/146862af-0a7d-443b-833b-afe237114f86.png"
    },
    {
        "_id": "16",
        "title": "Perforated Wide Tips Roach - Raw",
        "quantity": "1 pack (50 pieces)",
        "mrp": "50",
        "price": "49",
        "category": "Rolling paper & tobacco",
        "image": "Images/7006c28c-1ebd-4a7e-91ce-4d1c88593404.jpg"
    },
    {
        "_id": "17",
        "title": "Perfect Rolled Cones (Natural) - Bongchie",
        "quantity": "3 Pack",
        "mrp": "45",
        "price": "45",
        "category": "Rolling paper & tobacco",
        "image": "Images/62a43114-df35-461b-80a4-83c5544fde66.png"
    },
    {
        "_id": "18",
        "title": "Thins Pre-Rolled Rolling Paper - LIT",
        "quantity": "1 Pack",
        "mrp": "25",
        "price": "25",
        "category": "Rolling paper & tobacco",
        "image": "Images/8d385b40-e78b-434a-962d-50ba667891bf.png"
    },
    {
        "_id": "19",
        "title": "Ultimate Rolling Paper with Filter Tips & Crushing Tray (King Size, Bleached) - Mozo",
        "quantity": "32 Leaves + 32 Filters",
        "mrp": "80",
        "price": "80",
        "category": "Rolling paper & tobacco",
        "image": "Images/2a6eb6af-8143-4195-a788-c350255a8e1e.png"
    },
    {
        "_id": "20",
        "title": "Brown Classic Slim Rolling Paper (King Size) - Raw",
        "quantity": "32 pieces",
        "mrp": "80",
        "price": "79",
        "category": "Rolling paper & tobacco",
        "image": "Images/amul-toned.png"
    },
    {
        "_id": "6",
        "title": "English Oven Premium White Bread 350 g",
        "quantity": "350 g",
        "mrp": "30",
        "price": "27",
        "category": "Rolling paper & tobacco",
        "image": "Images/81136a7e-0681-4376-a109-92550ae66877.png"
    },
    {
        "_id": "7",
        "title": "Amul Cow Milk",
        "quantity": "500 ml",
        "mrp": "30",
        "price": "32",
        "category": "Rolling paper & tobacco",
        "image": "Images/ae29e828-f5d9-4f8b-89b6-8c6d6919df7b.png"
    },
    {
        "_id": "8",
        "title": "BranO Shaanegomti Premium White Bread",
        "quantity": "360 g (13 pieces)",
        "mrp": "40",
        "price": "40",
        "category": "Rolling paper & tobacco",
        "image": "Images/a858c12c-b0d7-408f-811c-52ed8c9b7223.png"
    },
    {
        "_id": "9",
        "title": "Amul Masti Cup Curd",
        "quantity": "200 g",
        "mrp": "120",
        "price": "120",
        "category": "Rolling paper & tobacco",
        "image": "Images/e47341cd-d920-4c0a-a9f2-20d663976cd0.png"
    },
    {
        "_id": "10",
        "title": "Amul Blend Diced Cheese",
        "quantity": "500 ml",
        "mrp": "35",
        "price": "32",
        "category": "Rolling paper & tobacco",
        "image": "Images/dfa345bf-052e-4657-ae4f-859bfe45fecf.png"
    },
    {
        "_id": "11",
        "title": "Amul Salted Butter",
        "quantity": "200 g",
        "mrp": "119",
        "price": "118",
        "category": "Rolling paper & tobacco",
        "image": "Images/03af3633-5fa5-438f-bece-145ed114d279.png"
    },
    {
        "_id": "12",
        "title": "Amul Cheese Slices",
        "quantity": "200 g",
        "mrp": "140",
        "price": "140",
        "category": "Rolling paper & tobacco",
        "image": "Images/a501e65f-194b-4db2-abc9-6b7bb515349c.png"
    },
    {
        "_id": "13",
        "title": "Amul Masti Pouch Curd",
        "quantity": "1 kg",
        "mrp": "77",
        "price": "77",
        "category": "Rolling paper & tobacco",
        "image": "Images/e7023096-622d-4e2e-9c2c-a7689262c36f.png"
    },
    {
        "_id": "14",
        "title": "BranO Bombay Pav",
        "quantity": "250 g",
        "mrp": "40",
        "price": "40",
        "category": "Rolling paper & tobacco",
        "image": "Images/d619dafc-96bc-4bd2-8e5b-f7f80c963431.png"
    },
    {
        "_id": "15",
        "title": "BranO Plus Brown Bread",
        "quantity": "270 g",
        "mrp": "35",
        "price": "35",
        "category": "Rolling paper & tobacco",
        "image": "Images/146862af-0a7d-443b-833b-afe237114f86.png"
    },
    {
        "_id": "1",
        "title": "Amul Gold Full Cream Milk",
        "quantity": "500 ml",
        "mrp": "35",
        "price": "32",
        "category": "Snacks & Munchies",
        "image": "Images/milk.png"
    },
    {
        "_id": "2",
        "title": "Amul Masti Pouch Curd",
        "quantity": "390 g",
        "mrp": "35",
        "price": "32",
        "category": "Snacks & Munchies",
        "image": "Images/whey.png"
    },
    {
        "_id": "3",
        "title": "Amul Salted Butter",
        "quantity": "100 g",
        "mrp": "58",
        "price": "54",
        "category": "Snacks & Munchies",
        "image": "Images/butter.png"
    },
    {
        "_id": "4",
        "title": "Good Morning Malai Milk Bread",
        "quantity": "400 g",
        "mrp": "40",
        "price": "40",
        "category": "Snacks & Munchies",
        "image": "Images/good-morning.png"
    },
    {
        "_id": "5",
        "title": "Amul Taza Toned Milk",
        "quantity": "500 ml",
        "mrp": "29",
        "price": "29",
        "category": "Snacks & Munchies",
        "image": "Images/amul-toned.png"
    },
    {
        "_id": "6",
        "title": "English Oven Premium White Bread 350 g",
        "quantity": "350 g",
        "mrp": "30",
        "price": "27",
        "category": "Snacks & Munchies",
        "image": "Images/81136a7e-0681-4376-a109-92550ae66877.png"
    },
    {
        "_id": "7",
        "title": "Amul Cow Milk",
        "quantity": "500 ml",
        "mrp": "30",
        "price": "32",
        "category": "Snacks & Munchies",
        "image": "Images/ae29e828-f5d9-4f8b-89b6-8c6d6919df7b.png"
    },
    {
        "_id": "8",
        "title": "BranO Shaanegomti Premium White Bread",
        "quantity": "360 g (13 pieces)",
        "mrp": "40",
        "price": "40",
        "category": "Snacks & Munchies",
        "image": "Images/a858c12c-b0d7-408f-811c-52ed8c9b7223.png"
    },
    {
        "_id": "9",
        "title": "Amul Masti Cup Curd",
        "quantity": "200 g",
        "mrp": "120",
        "price": "120",
        "category": "Snacks & Munchies",
        "image": "Images/e47341cd-d920-4c0a-a9f2-20d663976cd0.png"
    },
    {
        "_id": "10",
        "title": "Amul Blend Diced Cheese",
        "quantity": "500 ml",
        "mrp": "35",
        "price": "32",
        "category": "Snacks & Munchies",
        "image": "Images/dfa345bf-052e-4657-ae4f-859bfe45fecf.png"
    },
    {
        "_id": "11",
        "title": "Amul Salted Butter",
        "quantity": "200 g",
        "mrp": "119",
        "price": "118",
        "category": "Snacks & Munchies",
        "image": "Images/03af3633-5fa5-438f-bece-145ed114d279.png"
    },
    {
        "_id": "12",
        "title": "Amul Cheese Slices",
        "quantity": "200 g",
        "mrp": "140",
        "price": "140",
        "category": "Snacks & Munchies",
        "image": "Images/a501e65f-194b-4db2-abc9-6b7bb515349c.png"
    },
    {
        "_id": "13",
        "title": "Amul Masti Pouch Curd",
        "quantity": "1 kg",
        "mrp": "77",
        "price": "77",
        "category": "Snacks & Munchies",
        "image": "Images/e7023096-622d-4e2e-9c2c-a7689262c36f.png"
    },
    {
        "_id": "14",
        "title": "BranO Bombay Pav",
        "quantity": "250 g",
        "mrp": "40",
        "price": "40",
        "category": "Snacks & Munchies",
        "image": "Images/d619dafc-96bc-4bd2-8e5b-f7f80c963431.png"
    },
    {
        "_id": "15",
        "title": "BranO Plus Brown Bread",
        "quantity": "270 g",
        "mrp": "35",
        "price": "35",
        "category": "Snacks & Munchies",
        "image": "Images/146862af-0a7d-443b-833b-afe237114f86.png"
    },
    {
        "_id": "1",
        "title": "Amul Gold Full Cream Milk",
        "quantity": "500 ml",
        "mrp": "35",
        "price": "32",
        "category": "Hookah",
        "image": "Images/milk.png"
    },
    {
        "_id": "2",
        "title": "Amul Masti Pouch Curd",
        "quantity": "390 g",
        "mrp": "35",
        "price": "32",
        "category": "Hookah",
        "image": "Images/whey.png"
    },
    {
        "_id": "3",
        "title": "Amul Salted Butter",
        "quantity": "100 g",
        "mrp": "58",
        "price": "54",
        "category": "Hookah",
        "image": "Images/butter.png"
    },
    {
        "_id": "4",
        "title": "Good Morning Malai Milk Bread",
        "quantity": "400 g",
        "mrp": "40",
        "price": "40",
        "category": "Hookah",
        "image": "Images/good-morning.png"
    },
    {
        "_id": "5",
        "title": "Amul Taza Toned Milk",
        "quantity": "500 ml",
        "mrp": "29",
        "price": "29",
        "category": "Hookah",
        "image": "Images/amul-toned.png"
    },
    {
        "_id": "6",
        "title": "English Oven Premium White Bread 350 g",
        "quantity": "350 g",
        "mrp": "30",
        "price": "27",
        "category": "Hookah",
        "image": "Images/81136a7e-0681-4376-a109-92550ae66877.png"
    },
    {
        "_id": "7",
        "title": "Amul Cow Milk",
        "quantity": "500 ml",
        "mrp": "30",
        "price": "32",
        "category": "Hookah",
        "image": "Images/ae29e828-f5d9-4f8b-89b6-8c6d6919df7b.png"
    },
    {
        "_id": "8",
        "title": "BranO Shaanegomti Premium White Bread",
        "quantity": "360 g (13 pieces)",
        "mrp": "40",
        "price": "40",
        "category": "Hookah",
        "image": "Images/a858c12c-b0d7-408f-811c-52ed8c9b7223.png"
    },
    {
        "_id": "9",
        "title": "Amul Masti Cup Curd",
        "quantity": "200 g",
        "mrp": "120",
        "price": "120",
        "category": "Hookah",
        "image": "Images/e47341cd-d920-4c0a-a9f2-20d663976cd0.png"
    },
    {
        "_id": "10",
        "title": "Amul Blend Diced Cheese",
        "quantity": "500 ml",
        "mrp": "35",
        "price": "32",
        "category": "Hookah",
        "image": "Images/dfa345bf-052e-4657-ae4f-859bfe45fecf.png"
    },
    {
        "_id": "11",
        "title": "Amul Salted Butter",
        "quantity": "200 g",
        "mrp": "119",
        "price": "118",
        "category": "Hookah",
        "image": "Images/03af3633-5fa5-438f-bece-145ed114d279.png"
    },
    {
        "_id": "12",
        "title": "Amul Cheese Slices",
        "quantity": "200 g",
        "mrp": "140",
        "price": "140",
        "category": "Hookah",
        "image": "Images/a501e65f-194b-4db2-abc9-6b7bb515349c.png"
    },
    {
        "_id": "13",
        "title": "Amul Masti Pouch Curd",
        "quantity": "1 kg",
        "mrp": "77",
        "price": "77",
        "category": "Hookah",
        "image": "Images/e7023096-622d-4e2e-9c2c-a7689262c36f.png"
    },
    {
        "_id": "14",
        "title": "BranO Bombay Pav",
        "quantity": "250 g",
        "mrp": "40",
        "price": "40",
        "category": "Hookah",
        "image": "Images/d619dafc-96bc-4bd2-8e5b-f7f80c963431.png"
    },
    {
        "_id": "15",
        "title": "BranO Plus Brown Bread",
        "quantity": "270 g",
        "mrp": "35",
        "price": "35",
        "category": "Hookah",
        "image": "Images/146862af-0a7d-443b-833b-afe237114f86.png"
    },
    {
        "_id": "1",
        "title": "Amul Gold Full Cream Milk",
        "quantity": "500 ml",
        "mrp": "35",
        "price": "32",
        "category": "Mouth fresheners",
        "image": "Images/milk.png"
    },
    {
        "_id": "2",
        "title": "Amul Masti Pouch Curd",
        "quantity": "390 g",
        "mrp": "35",
        "price": "32",
        "category": "Mouth fresheners",
        "image": "Images/whey.png"
    },
    {
        "_id": "3",
        "title": "Amul Salted Butter",
        "quantity": "100 g",
        "mrp": "58",
        "price": "54",
        "category": "Mouth fresheners",
        "image": "Images/butter.png"
    },
    {
        "_id": "4",
        "title": "Good Morning Malai Milk Bread",
        "quantity": "400 g",
        "mrp": "40",
        "price": "40",
        "category": "Mouth fresheners",
        "image": "Images/good-morning.png"
    },
    {
        "_id": "5",
        "title": "Amul Taza Toned Milk",
        "quantity": "500 ml",
        "mrp": "29",
        "price": "29",
        "category": "Mouth fresheners",
        "image": "Images/amul-toned.png"
    },
    {
        "_id": "6",
        "title": "English Oven Premium White Bread 350 g",
        "quantity": "350 g",
        "mrp": "30",
        "price": "27",
        "category": "Mouth fresheners",
        "image": "Images/81136a7e-0681-4376-a109-92550ae66877.png"
    },
    {
        "_id": "7",
        "title": "Amul Cow Milk",
        "quantity": "500 ml",
        "mrp": "30",
        "price": "32",
        "category": "Mouth fresheners",
        "image": "Images/ae29e828-f5d9-4f8b-89b6-8c6d6919df7b.png"
    },
    {
        "_id": "8",
        "title": "BranO Shaanegomti Premium White Bread",
        "quantity": "360 g (13 pieces)",
        "mrp": "40",
        "price": "40",
        "category": "Mouth fresheners",
        "image": "Images/a858c12c-b0d7-408f-811c-52ed8c9b7223.png"
    },
    {
        "_id": "9",
        "title": "Amul Masti Cup Curd",
        "quantity": "200 g",
        "mrp": "120",
        "price": "120",
        "category": "Mouth fresheners",
        "image": "Images/e47341cd-d920-4c0a-a9f2-20d663976cd0.png"
    },
    {
        "_id": "10",
        "title": "Amul Blend Diced Cheese",
        "quantity": "500 ml",
        "mrp": "35",
        "price": "32",
        "category": "Mouth fresheners",
        "image": "Images/dfa345bf-052e-4657-ae4f-859bfe45fecf.png"
    },
    {
        "_id": "11",
        "title": "Amul Salted Butter",
        "quantity": "200 g",
        "mrp": "119",
        "price": "118",
        "category": "Mouth fresheners",
        "image": "Images/03af3633-5fa5-438f-bece-145ed114d279.png"
    },
    {
        "_id": "12",
        "title": "Amul Cheese Slices",
        "quantity": "200 g",
        "mrp": "140",
        "price": "140",
        "category": "Mouth fresheners",
        "image": "Images/a501e65f-194b-4db2-abc9-6b7bb515349c.png"
    },
    {
        "_id": "13",
        "title": "Amul Masti Pouch Curd",
        "quantity": "1 kg",
        "mrp": "77",
        "price": "77",
        "category": "Mouth fresheners",
        "image": "Images/e7023096-622d-4e2e-9c2c-a7689262c36f.png"
    },
    {
        "_id": "14",
        "title": "BranO Bombay Pav",
        "quantity": "250 g",
        "mrp": "40",
        "price": "40",
        "category": "Mouth fresheners",
        "image": "Images/d619dafc-96bc-4bd2-8e5b-f7f80c963431.png"
    },
    {
        "_id": "15",
        "title": "BranO Plus Brown Bread",
        "quantity": "270 g",
        "mrp": "35",
        "price": "35",
        "category": "Mouth fresheners",
        "image": "Images/146862af-0a7d-443b-833b-afe237114f86.png"
    },
    {
        "_id": "1",
        "title": "Amul Gold Full Cream Milk",
        "quantity": "500 ml",
        "mrp": "35",
        "price": "32",
        "category": "Cold Drinks & Juices",
        "image": "Images/milk.png"
    },
    {
        "_id": "2",
        "title": "Amul Masti Pouch Curd",
        "quantity": "390 g",
        "mrp": "35",
        "price": "32",
        "category": "Cold Drinks & Juices",
        "image": "Images/whey.png"
    },
    {
        "_id": "3",
        "title": "Amul Salted Butter",
        "quantity": "100 g",
        "mrp": "58",
        "price": "54",
        "category": "Cold Drinks & Juices",
        "image": "Images/butter.png"
    },
    {
        "_id": "4",
        "title": "Good Morning Malai Milk Bread",
        "quantity": "400 g",
        "mrp": "40",
        "price": "40",
        "category": "Cold Drinks & Juices",
        "image": "Images/good-morning.png"
    },
    {
        "_id": "5",
        "title": "Amul Taza Toned Milk",
        "quantity": "500 ml",
        "mrp": "29",
        "price": "29",
        "category": "Cold Drinks & Juices",
        "image": "Images/amul-toned.png"
    },
    {
        "_id": "6",
        "title": "English Oven Premium White Bread 350 g",
        "quantity": "350 g",
        "mrp": "30",
        "price": "27",
        "category": "Cold Drinks & Juices",
        "image": "Images/81136a7e-0681-4376-a109-92550ae66877.png"
    },
    {
        "_id": "7",
        "title": "Amul Cow Milk",
        "quantity": "500 ml",
        "mrp": "30",
        "price": "32",
        "category": "Cold Drinks & Juices",
        "image": "Images/ae29e828-f5d9-4f8b-89b6-8c6d6919df7b.png"
    },
    {
        "_id": "8",
        "title": "BranO Shaanegomti Premium White Bread",
        "quantity": "360 g (13 pieces)",
        "mrp": "40",
        "price": "40",
        "category": "Cold Drinks & Juices",
        "image": "Images/a858c12c-b0d7-408f-811c-52ed8c9b7223.png"
    },
    {
        "_id": "9",
        "title": "Amul Masti Cup Curd",
        "quantity": "200 g",
        "mrp": "120",
        "price": "120",
        "category": "Cold Drinks & Juices",
        "image": "Images/e47341cd-d920-4c0a-a9f2-20d663976cd0.png"
    },
    {
        "_id": "10",
        "title": "Amul Blend Diced Cheese",
        "quantity": "500 ml",
        "mrp": "35",
        "price": "32",
        "category": "Cold Drinks & Juices",
        "image": "Images/dfa345bf-052e-4657-ae4f-859bfe45fecf.png"
    },
    {
        "_id": "11",
        "title": "Amul Salted Butter",
        "quantity": "200 g",
        "mrp": "119",
        "price": "118",
        "category": "Cold Drinks & Juices",
        "image": "Images/03af3633-5fa5-438f-bece-145ed114d279.png"
    },
    {
        "_id": "12",
        "title": "Amul Cheese Slices",
        "quantity": "200 g",
        "mrp": "140",
        "price": "140",
        "category": "Cold Drinks & Juices",
        "image": "Images/a501e65f-194b-4db2-abc9-6b7bb515349c.png"
    },
    {
        "_id": "13",
        "title": "Amul Masti Pouch Curd",
        "quantity": "1 kg",
        "mrp": "77",
        "price": "77",
        "category": "Cold Drinks & Juices",
        "image": "Images/e7023096-622d-4e2e-9c2c-a7689262c36f.png"
    },
    {
        "_id": "14",
        "title": "BranO Bombay Pav",
        "quantity": "250 g",
        "mrp": "40",
        "price": "40",
        "category": "Cold Drinks & Juices",
        "image": "Images/d619dafc-96bc-4bd2-8e5b-f7f80c963431.png"
    },
    {
        "_id": "15",
        "title": "BranO Plus Brown Bread",
        "quantity": "270 g",
        "mrp": "35",
        "price": "35",
        "category": "Cold Drinks & Juices",
        "image": "Images/146862af-0a7d-443b-833b-afe237114f86.png"
    },
    {
        "_id": "1",
        "title": "Amul Gold Full Cream Milk",
        "quantity": "500 ml",
        "mrp": "35",
        "price": "32",
        "category": "Candies & Gums",
        "image": "Images/milk.png"
    },
    {
        "_id": "2",
        "title": "Amul Masti Pouch Curd",
        "quantity": "390 g",
        "mrp": "35",
        "price": "32",
        "category": "Candies & Gums",
        "image": "Images/whey.png"
    },
    {
        "_id": "3",
        "title": "Amul Salted Butter",
        "quantity": "100 g",
        "mrp": "58",
        "price": "54",
        "category": "Candies & Gums",
        "image": "Images/butter.png"
    },
    {
        "_id": "4",
        "title": "Good Morning Malai Milk Bread",
        "quantity": "400 g",
        "mrp": "40",
        "price": "40",
        "category": "Candies & Gums",
        "image": "Images/good-morning.png"
    },
    {
        "_id": "5",
        "title": "Amul Taza Toned Milk",
        "quantity": "500 ml",
        "mrp": "29",
        "price": "29",
        "category": "Candies & Gums",
        "image": "Images/amul-toned.png"
    },
    {
        "_id": "6",
        "title": "English Oven Premium White Bread 350 g",
        "quantity": "350 g",
        "mrp": "30",
        "price": "27",
        "category": "Candies & Gums",
        "image": "Images/81136a7e-0681-4376-a109-92550ae66877.png"
    },
    {
        "_id": "7",
        "title": "Amul Cow Milk",
        "quantity": "500 ml",
        "mrp": "30",
        "price": "32",
        "category": "Candies & Gums",
        "image": "Images/ae29e828-f5d9-4f8b-89b6-8c6d6919df7b.png"
    },
    {
        "_id": "8",
        "title": "BranO Shaanegomti Premium White Bread",
        "quantity": "360 g (13 pieces)",
        "mrp": "40",
        "price": "40",
        "category": "Candies & Gums",
        "image": "Images/a858c12c-b0d7-408f-811c-52ed8c9b7223.png"
    },
    {
        "_id": "9",
        "title": "Amul Masti Cup Curd",
        "quantity": "200 g",
        "mrp": "120",
        "price": "120",
        "category": "Candies & Gums",
        "image": "Images/e47341cd-d920-4c0a-a9f2-20d663976cd0.png"
    },
    {
        "_id": "10",
        "title": "Amul Blend Diced Cheese",
        "quantity": "500 ml",
        "mrp": "35",
        "price": "32",
        "category": "Candies & Gums",
        "image": "Images/dfa345bf-052e-4657-ae4f-859bfe45fecf.png"
    },
    {
        "_id": "11",
        "title": "Amul Salted Butter",
        "quantity": "200 g",
        "mrp": "119",
        "price": "118",
        "category": "Candies & Gums",
        "image": "Images/03af3633-5fa5-438f-bece-145ed114d279.png"
    },
    {
        "_id": "12",
        "title": "Amul Cheese Slices",
        "quantity": "200 g",
        "mrp": "140",
        "price": "140",
        "category": "Candies & Gums",
        "image": "Images/a501e65f-194b-4db2-abc9-6b7bb515349c.png"
    },
    {
        "_id": "13",
        "title": "Amul Masti Pouch Curd",
        "quantity": "1 kg",
        "mrp": "77",
        "price": "77",
        "category": "Candies & Gums",
        "image": "Images/e7023096-622d-4e2e-9c2c-a7689262c36f.png"
    },
    {
        "_id": "14",
        "title": "BranO Bombay Pav",
        "quantity": "250 g",
        "mrp": "40",
        "price": "40",
        "category": "Candies & Gums",
        "image": "Images/d619dafc-96bc-4bd2-8e5b-f7f80c963431.png"
    },
    {
        "_id": "15",
        "title": "BranO Plus Brown Bread",
        "quantity": "270 g",
        "mrp": "35",
        "price": "35",
        "category": "Candies & Gums",
        "image": "Images/146862af-0a7d-443b-833b-afe237114f86.png"
    }
]